README.md
setup.py
tba_api_v3client.egg-info/PKG-INFO
tba_api_v3client.egg-info/SOURCES.txt
tba_api_v3client.egg-info/dependency_links.txt
tba_api_v3client.egg-info/requires.txt
tba_api_v3client.egg-info/top_level.txt
tbaapiv3client/__init__.py
tbaapiv3client/api_client.py
tbaapiv3client/configuration.py
tbaapiv3client/exceptions.py
tbaapiv3client/rest.py
tbaapiv3client/api/__init__.py
tbaapiv3client/api/district_api.py
tbaapiv3client/api/event_api.py
tbaapiv3client/api/list_api.py
tbaapiv3client/api/match_api.py
tbaapiv3client/api/tba_api.py
tbaapiv3client/api/team_api.py
tbaapiv3client/models/__init__.py
tbaapiv3client/models/api_status.py
tbaapiv3client/models/api_status_app_version.py
tbaapiv3client/models/award.py
tbaapiv3client/models/award_recipient.py
tbaapiv3client/models/district_list.py
tbaapiv3client/models/district_ranking.py
tbaapiv3client/models/district_ranking_event_points.py
tbaapiv3client/models/elimination_alliance.py
tbaapiv3client/models/elimination_alliance_backup.py
tbaapiv3client/models/elimination_alliance_status.py
tbaapiv3client/models/event.py
tbaapiv3client/models/event_district_points.py
tbaapiv3client/models/event_district_points_points.py
tbaapiv3client/models/event_district_points_tiebreakers.py
tbaapiv3client/models/event_insights.py
tbaapiv3client/models/event_insights2016.py
tbaapiv3client/models/event_insights2017.py
tbaapiv3client/models/event_insights2018.py
tbaapiv3client/models/event_op_rs.py
tbaapiv3client/models/event_ranking.py
tbaapiv3client/models/event_ranking_extra_stats_info.py
tbaapiv3client/models/event_ranking_rankings.py
tbaapiv3client/models/event_ranking_sort_order_info.py
tbaapiv3client/models/event_simple.py
tbaapiv3client/models/match.py
tbaapiv3client/models/match_alliance.py
tbaapiv3client/models/match_alliances.py
tbaapiv3client/models/match_score_breakdown2015.py
tbaapiv3client/models/match_score_breakdown2015_alliance.py
tbaapiv3client/models/match_score_breakdown2016.py
tbaapiv3client/models/match_score_breakdown2016_alliance.py
tbaapiv3client/models/match_score_breakdown2017.py
tbaapiv3client/models/match_score_breakdown2017_alliance.py
tbaapiv3client/models/match_score_breakdown2018.py
