Metadata-Version: 1.0
Name: tba-api-v3client
Version: 3.5
Summary: The Blue Alliance API v3
Home-page: UNKNOWN
Author: UNKNOWN
Author-email: UNKNOWN
License: UNKNOWN
Keywords: OpenAPI,OpenAPI-Generator,The Blue Alliance API v3
Platform: UNKNOWN
